{
  "schema_version": 2,
  "updated_at": "2026-07-14",
  "note": "玉兔6 通用能力注册表。系统能力随发行版安装，具体项目能力通过 project-packs 独立接入。",
  "workspace_modules_dir": "shared/capability_registry/modules",
  "policy": {
    "lookup_first_for": [
      "persistent local customizations",
      "previously configured features",
      "Hermes/Yutu voice workflow",
      "Feishu integrations",
      "multi-agent collaboration",
      "agent capability contracts",
      "ASR hotwords and corrections"
    ],
    "do_not_store": [
      "API keys",
      "passwords",
      "private tokens",
      "cookies",
      "full secrets from .env"
    ],
    "instruction_expansion_priority": [
      "explicit_named_skill_or_agent",
      "installed_project_pack",
      "cross_project_wrapper",
      "global_instruction_expansion_router"
    ],
    "project_boundary": "具体项目的 agent、skill、发布流程和业务资料不得进入通用发行版；项目能力包安装后才登记。",
    "project_pack_contract": "project-packs/README.md"
  },
  "modules": [
    {
      "id": "multi-agent-collaboration-contract",
      "status": "present_in_workspace",
      "path": "shared/capability_registry/modules/multi-agent-collaboration-contract",
      "summary": "系统智能体的能力目录、职责边界与交接契约。",
      "keywords": [
        "multi-agent",
        "多智能体",
        "协作",
        "能力目录",
        "接口契约",
        "handoff",
        "Codex"
      ]
    },
    {
      "id": "hermes-yutu-voice-bridge",
      "status": "present_in_workspace",
      "path": "shared/capability_registry/modules/hermes-yutu-voice-bridge",
      "summary": "可选的玉兔语音、飞书通知、ASR 纠错与搜索桥接能力。",
      "keywords": [
        "玉兔",
        "Hermes",
        "语音唤醒",
        "飞书",
        "确认消息",
        "ASR",
        "热词",
        "纠错"
      ]
    },
    {
      "id": "instruction-expansion-router",
      "status": "present_in_workspace",
      "path": "shared/capability_registry/modules/instruction-expansion-router",
      "summary": "前门指令补齐路由器；把口语、简略、截图或跨项目指令补成完整任务信封。",
      "keywords": [
        "指令补齐",
        "instruction expansion",
        "前门",
        "口语",
        "截图",
        "跨项目",
        "task envelope"
      ]
    },
    {
      "id": "self-reflection-optimizer",
      "status": "present_in_workspace",
      "path": "shared/capability_registry/modules/self-reflection-optimizer",
      "summary": "对指定模块挑刺并沉淀可复用改进；争议或高风险变更交给主人拍板。",
      "keywords": [
        "自省优化",
        "反思优化",
        "模块复盘",
        "优秀案例",
        "owner decision"
      ]
    },
    {
      "id": "meowa-game-assets",
      "status": "present_in_workspace",
      "path": "shared/capability_registry/modules/meowa-game-assets",
      "summary": "可选的共享游戏素材生成能力；授权给秘书、执行智能体及已安装项目部门。",
      "keywords": [
        "Meowa",
        "MeowArt",
        "game assets",
        "游戏素材",
        "pixel art",
        "sprite",
        "tileset",
        "animation"
      ]
    },
    {
      "id": "peekaboo-desktop-control",
      "type": "runner",
      "status": "optional_external",
      "registered_in": "shared/routing/runners.yaml (id=peekaboo)",
      "summary": "可选 GUI 控制 runner；安装并授予屏幕录制和辅助功能权限后可截图、点击、输入和滚动。",
      "keywords": [
        "peekaboo",
        "GUI",
        "桌面控制",
        "点击",
        "截屏",
        "accessibility"
      ]
    }
  ],
  "skills": {
    "archive": {
      "path": "knowledge/corpus/codex-skills",
      "scope": "generic_only"
    },
    "global_expander": {
      "id": "instruction-expansion-router",
      "status": "present_in_workspace"
    },
    "project_skills": {
      "status": "not_bundled",
      "install_contract": "project-packs/README.md",
      "registration": "knowledge/corpus/codex-skills/skills/project-routes/<projectId>.md"
    },
    "manifest": "skills-manifest.md"
  }
}
